stone_statistics/__init__.py
stone_statistics/example.py
stone_statistics/stat.py
stone_statistics/finder/__init__.py
stone_statistics/finder/representative_value_finder.py
stones_statistics-0.2.0.dist-info/LICENSE
stones_statistics-0.2.0.dist-info/METADATA
stones_statistics-0.2.0.dist-info/WHEEL
stones_statistics-0.2.0.dist-info/top_level.txt
stones_statistics-0.2.0.dist-info/RECORD
