Metadata-Version: 2.1
Name: stones_statistics
Version: 0.2.0
Summary: Stone's Statistics Library
Home-page: https://github.com/seoggeonjin/stone_statistics
Download-URL: https://github.com/seoggeonjin/stone_statistics/archive/master.zip
Author: Stone
Author-email: seoggeonjin@gmail.com
Classifier: Programming Language :: Python :: 3
Classifier: License :: OSI Approved :: MIT License
Classifier: Operating System :: OS Independent
Requires-Python: >=3.12
License-File: LICENSE
Requires-Dist: Fraction >=2.2.0
